cdk_webapp_skeleton/__init__.py
cdk_webapp_skeleton/auth_stack.py
cdk_webapp_skeleton/branch_cicd_pipeline.py
cdk_webapp_skeleton/branch_config.py
cdk_webapp_skeleton/monitored_lambda_function.py
cdk_webapp_skeleton/py.typed
cdk_webapp_skeleton/react_website.py
cdk_webapp_skeleton/test_utils.py
cdk_webapp_skeleton/webapp_lambda.py
cdk_webapp_skeleton-0.9.11.dist-info/METADATA
cdk_webapp_skeleton-0.9.11.dist-info/WHEEL
cdk_webapp_skeleton-0.9.11.dist-info/RECORD
