Metadata-Version: 2.3
Name: cdk-webapp-skeleton
Version: 0.9.11
Summary: 
Author: Ilya Nekhay
Author-email: nekhayiv@gmail.com
Requires-Python: >=3.9,<4
Classifier: Programming Language :: Python :: 3
Classifier: Programming Language :: Python :: 3.9
Classifier: Programming Language :: Python :: 3.10
Classifier: Programming Language :: Python :: 3.11
Classifier: Programming Language :: Python :: 3.12
Classifier: Programming Language :: Python :: 3.13
Requires-Dist: aws-cdk-lib (>=2.67.0,<3.0.0)
Requires-Dist: cloudcomponents-cdk-static-website (>=2.2.0,<3.0.0)
